catslog.py
catslog-1.0.9.dist-info/LICENSE
catslog-1.0.9.dist-info/METADATA
catslog-1.0.9.dist-info/WHEEL
catslog-1.0.9.dist-info/top_level.txt
catslog-1.0.9.dist-info/RECORD
