Metadata-Version: 2.1
Name: catslog
Version: 1.0.9
Summary: Logs the execution of the wrapped function and, if applicable, does a basic handling of the raised exception. Please check the github page for more detailed instructions
Home-page: https://github.com/PeriGK/catslog
Author: Periklis Gkolias
Author-email: per.gkolias@gmail.com
License: UNKNOWN
Keywords: exceptions exception-handling logging
Platform: UNKNOWN
Classifier: Development Status :: 4 - Beta
Classifier: Intended Audience :: Developers
Classifier: Topic :: Software Development
Classifier: License :: OSI Approved :: GNU General Public License v3 (GPLv3)
Classifier: Programming Language :: Python :: 3
Classifier: Programming Language :: Python :: 3.4
Classifier: Programming Language :: Python :: 3.5
Classifier: Programming Language :: Python :: 3.6
